FolderAnalyse/__init__.py
FolderAnalyse/example.txt
FolderAnalyse/fileparser.py
FolderAnalyse/process.py
FolderAnalyse/script.py
FolderAnalyse/test.txt
FolderAnalyse/test1.txt
FolderAnalyse/test2.txt
FolderAnalyse-0.2.0.dist-info/METADATA
FolderAnalyse-0.2.0.dist-info/WHEEL
FolderAnalyse-0.2.0.dist-info/entry_points.txt
FolderAnalyse-0.2.0.dist-info/top_level.txt
FolderAnalyse-0.2.0.dist-info/RECORD
