Metadata-Version: 2.1
Name: FolderAnalyse
Version: 0.2.0
Summary: A program that analyses files in a directory with word frequency statistics.
Home-page: http://github.com/rpep/FolderAnalyse
Author: Ryan Alexander Pepper
Author-email: ryan.pepper@soton.ac.uk
License: UNKNOWN
Project-URL: Documentation, https://folderanalyse.readthedocs.io
Project-URL: Source Code, https://github.com/rpep/FolderAnalyse
Platform: UNKNOWN
Classifier: Programming Language :: Python :: 3
Classifier: License :: OSI Approved :: MIT License
Classifier: Operating System :: OS Independent
Requires-Python: >= 3.6
Requires-Dist: pytest
